django_drapes
