Metadata-Version: 1.0
Name: django-drapes
Version: 0.1.2
Summary: Some decorators and classes to make working with django projects easier.
Home-page: UNKNOWN
Author: Ulas Tuerkmen
Author-email: afroisalreadyinu@gmail.com
License: UNKNOWN
Platform: UNKNOWN
Classifier: Framework :: Django
